pyjupiter/__init__.py
pyjupiter/exceptions.py
pyjupiter/clients/__init__.py
pyjupiter/clients/base_ultra_client.py
pyjupiter/clients/jupiter_client.py
pyjupiter/clients/ultra_api_client.py
pyjupiter/models/__init__.py
pyjupiter/models/base_model.py
pyjupiter/models/common/__init__.py
pyjupiter/models/common/dex_enum.py
pyjupiter/models/ultra_api/__init__.py
pyjupiter/models/ultra_api/ultra_execute_request_model.py
pyjupiter/models/ultra_api/ultra_order_request_model.py
pyjupiter-0.0.1.dist-info/METADATA
pyjupiter-0.0.1.dist-info/WHEEL
pyjupiter-0.0.1.dist-info/licenses/LICENSE
pyjupiter-0.0.1.dist-info/RECORD
