Metadata-Version: 2.4
Name: pyjupiter
Version: 0.0.1
Summary: High-performance sync/async Python SDK for Jupiter Exchange APIs, powered by curl_cffi.
Project-URL: homepage, https://github.com/solanab/pyjupiter
Project-URL: repository, https://github.com/solanab/pyjupiter
Author-email: solanab <whiredj@gmail.com>
License: MIT
License-File: LICENSE
Keywords: jupiter,sdk,solana
Classifier: Development Status :: 5 - Production/Stable
Classifier: Intended Audience :: Developers
Classifier: License :: OSI Approved :: MIT License
Classifier: Operating System :: OS Independent
Classifier: Programming Language :: Python :: 3
Classifier: Programming Language :: Python :: 3.9
Classifier: Programming Language :: Python :: 3.10
Classifier: Programming Language :: Python :: 3.11
Classifier: Programming Language :: Python :: 3.12
Classifier: Programming Language :: Python :: 3.13
Classifier: Topic :: Software Development :: Libraries :: Python Modules
Requires-Python: >=3.9.1
Requires-Dist: base58>=2.1.1
Requires-Dist: curl-cffi>=0.12
Requires-Dist: pydantic>=2.11.3
Requires-Dist: solders>=0.26.0
